be_patient/__init__.py
be_patient/api.py
be_patient/curler.py
be_patient/waiter_src/__init__.py
be_patient/waiter_src/checker.py
be_patient/waiter_src/comparators.py
be_patient/waiter_src/executor.py
be_patient/waiter_src/waiter.py
be_patient/waiter_src/checkers/__init__.py
be_patient/waiter_src/checkers/response_checkers.py
be_patient/waiter_src/exceptions/__init__.py
be_patient/waiter_src/exceptions/executor_exceptions.py
be_patient/waiter_src/exceptions/waiter_exceptions.py
be_patient/waiter_src/executors/__init__.py
be_patient/waiter_src/executors/requests_executor.py
be_patient-0.1.0.dist-info/LICENSE
be_patient-0.1.0.dist-info/METADATA
be_patient-0.1.0.dist-info/WHEEL
be_patient-0.1.0.dist-info/top_level.txt
be_patient-0.1.0.dist-info/RECORD
