Metadata-Version: 2.1
Name: be-patient
Version: 0.1.0
Summary: A library facilitating work with asynchronous APIs
Author-email: Dawid Szaniawski <webluduspl@gmail.com>
License: MIT License
Project-URL: repository, https://github.com/dawid-szaniawski/be_patient
Project-URL: documentation, https://webludus.pl
Keywords: api,async,api_testing,automation,json,testing,web
Classifier: Development Status :: 4 - Beta
Classifier: Environment :: Web Environment
Classifier: Intended Audience :: Developers
Classifier: Natural Language :: English
Classifier: Operating System :: OS Independent
Classifier: License :: OSI Approved :: MIT License
Classifier: Programming Language :: Python
Classifier: Programming Language :: Python :: 3.10
Classifier: Programming Language :: Python :: 3.11
Classifier: Programming Language :: Python :: 3 :: Only
Classifier: Programming Language :: Python :: Implementation :: CPython
Classifier: Topic :: Internet :: WWW/HTTP
Classifier: Topic :: Software Development :: Libraries
Classifier: Topic :: Software Development :: Testing
Classifier: Topic :: Software Development :: Quality Assurance
Classifier: Topic :: Utilities
Classifier: Topic :: File Formats :: JSON
Classifier: Topic :: File Formats :: JSON :: JSON Schema
Classifier: Typing :: Typed
Requires-Python: >=3.10
License-File: LICENSE
Requires-Dist: dictor (~=0.1.10)
Requires-Dist: requests (~=2.28.1)
Provides-Extra: dev
Requires-Dist: black (==23.7.0) ; extra == 'dev'
Requires-Dist: flake8 (==6.1.0) ; extra == 'dev'
Requires-Dist: isort (==5.12.0) ; extra == 'dev'
Requires-Dist: mypy (==1.4.1) ; extra == 'dev'
Requires-Dist: pytest (==7.4.0) ; extra == 'dev'
Requires-Dist: pytest-cov (==4.1.0) ; extra == 'dev'
Requires-Dist: pytest-mock (==3.11.1) ; extra == 'dev'
Requires-Dist: ruff (==0.0.282) ; extra == 'dev'
Requires-Dist: tox (==4.7.0) ; extra == 'dev'
Requires-Dist: twine (==4.0.2) ; extra == 'dev'
